RABiTPy/__init__.py
RABiTPy/capture.py
RABiTPy/constants.py
RABiTPy/identify.py
RABiTPy/stats.py
RABiTPy/track.py
RABiTPy/utils.py
RABiTPy-1.2.0.dist-info/LICENSE
RABiTPy-1.2.0.dist-info/METADATA
RABiTPy-1.2.0.dist-info/WHEEL
RABiTPy-1.2.0.dist-info/top_level.txt
RABiTPy-1.2.0.dist-info/RECORD
