Metadata-Version: 2.1
Name: RABiTPy
Version: 1.2.0
Summary: RABiTPy: A package to track the movement of a subject in a video file.
Home-page: https://github.com/indraneel207/RABiTPy
Author: Indraneel Vairagare
Author-email: indraneel207@gmail.com
Maintainer: Samyabrata Sen, Abhishek Shrivastava
Maintainer-email: ssen31@asu.edu, ashrivastava@asu.edu
License: MIT
Project-URL: Bug Reports, https://github.com/indraneel207/RABiTPy/issues
Project-URL: Source, https://github.com/indraneel207/RABiTPy
Keywords: tracking video analysis 2D
Classifier: Programming Language :: Python :: 3
Classifier: Programming Language :: Python :: 3.10
Classifier: License :: OSI Approved :: MIT License
Classifier: Operating System :: OS Independent
Requires-Python: >=3.10, <3.11
License-File: LICENSE
Requires-Dist: aicsimageio==4.14.0
Requires-Dist: distfit==1.7.3
Requires-Dist: ipywidgets==8.1.5
Requires-Dist: matplotlib==3.7.5
Requires-Dist: matplotlib-inline==0.1.6
Requires-Dist: numpy==1.24.4
Requires-Dist: natsort==8.4.0
Requires-Dist: omnipose>=1.0.6
Requires-Dist: opencv-python==4.9.0.80
Requires-Dist: opencv-python-headless==4.9.0.80
Requires-Dist: pandas==2.1.4
Requires-Dist: scikit-image==0.20.0
Requires-Dist: scikit-learn==1.4.2
Requires-Dist: scipy==1.13.0
Requires-Dist: seaborn==0.13.2
Requires-Dist: torch-optimizer==0.3.0
Requires-Dist: tqdm==4.66.2
Requires-Dist: trackpy==0.6.2
